pigsay/__init__.py
pigsay/converter.py
pigsay-0.1.0.dist-info/METADATA
pigsay-0.1.0.dist-info/WHEEL
pigsay-0.1.0.dist-info/entry_points.txt
pigsay-0.1.0.dist-info/RECORD
