Metadata-Version: 2.4
Name: pigsay
Version: 0.1.0
Summary: Add your description here
Author-email: woodwhale <woodwhale@qq.com>
Requires-Python: >=3.10
Requires-Dist: pycryptodome>=3.23.0
